<!DOCTYPE ui:UiBinder SYSTEM "http://dl.google.com/gwt/DTD/xhtml.ent">
<ui:UiBinder xmlns:ui="urn:ui:com.google.gwt.uibinder" xmlns:g="urn:import:com.google.gwt.user.client.ui"
	xmlns:c="urn:import:com.google.gwt.user.cellview.client" xmlns:p="urn:import:com.willshex.blogwt.client.part">
	<ui:import field="com.willshex.blogwt.client.page.PageType.EditPostPageType" />
	<ui:style>
	
	</ui:style>
	<g:HTMLPanel>
		<div class="jumbotron">
			<h1 ui:field="elTitle">Posts</h1>
			<p ui:field="elExtendedTitle" class="small">Extended Title</p>
		</div>

		<div class="btn-toolbar">
			<div class="btn-group">
				<g:InlineHyperlink ui:field="lnkNewPost" styleName="btn btn-default"
					targetHistoryToken="{EditPostPageType.asTargetHistoryToken}/new">
					<span class="glyphicon glyphicon-plus"></span>
					New Post
				</g:InlineHyperlink>
			</div>
		</div>

		<g:HTMLPanel>
			<c:CellList ui:field="clPosts" />
		</g:HTMLPanel>

		<g:HTMLPanel ui:field="pnlNoPosts">
			<h2 class="text-center">No posts! :'(</h2>
		</g:HTMLPanel>

		<p:BackToTop />
	</g:HTMLPanel>
</ui:UiBinder> 